django_skote/__init__.py
django_skote/apps.py
django_skote/settings.py
django_skote/static/django_skote/css/app-rtl.min.css
django_skote/static/django_skote/css/app-rtl.min.css.map
django_skote/static/django_skote/css/app.css
django_skote/static/django_skote/css/app.min.css
django_skote/static/django_skote/css/app.min.css.map
django_skote/static/django_skote/css/bootstrap-rtl.min.css
django_skote/static/django_skote/css/bootstrap-rtl.min.css.map
django_skote/static/django_skote/css/bootstrap.css
django_skote/static/django_skote/css/bootstrap.min.css
django_skote/static/django_skote/css/bootstrap.min.css.map
django_skote/static/django_skote/css/icons-rtl.min.css
django_skote/static/django_skote/css/icons-rtl.min.css.map
django_skote/static/django_skote/css/icons.css
django_skote/static/django_skote/css/icons.css.map
django_skote/static/django_skote/css/icons.min.css
django_skote/static/django_skote/css/icons.min.css.map
django_skote/static/django_skote/fonts/boxicons.eot
django_skote/static/django_skote/fonts/boxicons.svg
django_skote/static/django_skote/fonts/boxicons.ttf
django_skote/static/django_skote/fonts/boxicons.woff
django_skote/static/django_skote/fonts/boxicons.woff2
django_skote/static/django_skote/fonts/dripicons-v2.eot
django_skote/static/django_skote/fonts/dripicons-v2.svg
django_skote/static/django_skote/fonts/dripicons-v2.ttf
django_skote/static/django_skote/fonts/dripicons-v2.woff
django_skote/static/django_skote/fonts/fa-brands-400.eot
django_skote/static/django_skote/fonts/fa-brands-400.svg
django_skote/static/django_skote/fonts/fa-brands-400.ttf
django_skote/static/django_skote/fonts/fa-brands-400.woff
django_skote/static/django_skote/fonts/fa-brands-400.woff2
django_skote/static/django_skote/fonts/fa-regular-400.eot
django_skote/static/django_skote/fonts/fa-regular-400.svg
django_skote/static/django_skote/fonts/fa-regular-400.ttf
django_skote/static/django_skote/fonts/fa-regular-400.woff
django_skote-0.0.9.dist-info/LICENSE
django_skote-0.0.9.dist-info/METADATA
django_skote-0.0.9.dist-info/WHEEL
django_skote-0.0.9.dist-info/top_level.txt
django_skote-0.0.9.dist-info/RECORD
